LICENSE
NOTICE
README.md
pyproject.toml
setup.py
causaltune/__init__.py
causaltune/data_utils.py
causaltune/dataset_processor.py
causaltune/datasets.py
causaltune/memoizer.py
causaltune/optimiser.py
causaltune/remote.py
causaltune/shap.py
causaltune/utils.py
causaltune/visualizer.py
causaltune.egg-info/PKG-INFO
causaltune.egg-info/SOURCES.txt
causaltune.egg-info/dependency_links.txt
causaltune.egg-info/requires.txt
causaltune.egg-info/top_level.txt
causaltune/models/__init__.py
causaltune/models/dummy.py
causaltune/models/monkey_patch_flaml.py
causaltune/models/monkey_patches.py
causaltune/models/passthrough.py
causaltune/models/regression.py
causaltune/models/transformed_outcome.py
causaltune/models/wrapper.py
causaltune/score/__init__.py
causaltune/score/erupt.py
causaltune/score/erupt_core.py
causaltune/score/erupt_old.py
causaltune/score/r_score.py
causaltune/score/scoring.py
causaltune/score/thompson.py
causaltune/search/__init__.py
causaltune/search/component.py
causaltune/search/params.py
causaltune/thirdparty/__init__.py
causaltune/thirdparty/causalml/__init__.py
causaltune/thirdparty/causalml/metrics.py