Metadata-Version: 2.1
Name: causaltune
Version: 0.1.8
Summary: AutoML for Causal Inference.
Home-page: https://github.com/py-why/causaltune
Author: Wise
Keywords: causaltune
Classifier: Programming Language :: Python :: 3 :: Only
Classifier: Programming Language :: Python :: 3.8
Classifier: Programming Language :: Python :: 3.9
Classifier: Programming Language :: Python :: 3.10
Classifier: Programming Language :: Python :: 3.11
Provides-Extra: test
Provides-Extra: ray
License-File: LICENSE
License-File: NOTICE
